siinc/__init__.py
siinc/__main__.py
siinc/__version__.py
siinc/exceptions.py
siinc/models.py
siinc/py.typed
siinc/siinc.py
siinc/utils.py
siinc-0.0.1a1.dist-info/LICENSE
siinc-0.0.1a1.dist-info/METADATA
siinc-0.0.1a1.dist-info/WHEEL
siinc-0.0.1a1.dist-info/entry_points.txt
siinc-0.0.1a1.dist-info/top_level.txt
siinc-0.0.1a1.dist-info/RECORD
